Metadata-Version: 2.1
Name: testhttp
Version: 0.6.1
Summary: HTTP testing tool
Home-page: http://github.com/faisalraja/testhttp
Author: Faisal Raja
Author-email: support@altlimit.com
License: MIT
Keywords: http test api
Platform: UNKNOWN
